Workbook

Sheet Executive Dashboard
A1: SILVER SANDS RESORT & CASINO
A2: MONTHLY MANAGEMENT REPORT - MARCH 2025
A3: Revenue | B3: Budget Cost | C3: Actual Cost | D3: Variance % | E3: Occupancy % | F3: RevPAR | G3: COGS | H3: Maintenance Cost
A4: =SUM(tblFinancials[Revenue]) -> 47329088 | B4: =SUM(tblFinancials[Budgeted Cost]) -> 9634794 | C4: =SUM(tblFinancials[Actual Cost]) -> 10007416 | D4: =(C4-B4)/B4 -> 0.03867462 | E4: =AVERAGE(tblKPIs[Occupancy %])/100 -> 0.882 | F4: =AVERAGE(tblKPIs[RevPAR]) -> 206.46 | G4: =SUM(tblInventory[COGS]) -> 2688219 | H4: =SUM(tblMaintenance[Maintenance Cost]) -> 3166232

Sheet Executive Summary
A1: SILVER SANDS RESORT & CASINO
A2: MONTHLY MANAGEMENT REPORT - MARCH 2025
A3: Executive Summary
A5: Financial Performance
A6: Silver Sands Resort & Casino generated approximately $47.3 million in revenue during the reporting period. Actual operating costs exceeded budget by approximately 3.9%, indicating moderate unfavorable variance versus plan. Housekeeping recorded the largest departmental variance at approximately $148,128, representing roughly 8% above budget.
A8: Operational Performance
A9: Property performance remained strong throughout the reporting period, with average occupancy of approximately 88.2% and RevPAR of approximately $206.46. These results indicate healthy demand levels and effective room revenue performance. Occupancy and RevPAR trends remained stable throughout the reporting period, supporting overall revenue performance.
A11: Inventory & COGS
A12: Total Cost of Goods Sold (COGS) was approximately $2.7 million during the reporting period. The Dairy category represented the largest COGS component at approximately $58,291, with a COGS rate of roughly 83.1%.
A14: Maintenance Review
A15: Total maintenance spending was approximately $3.2 million. Gaming Operations generated the highest maintenance expenditure at approximately $759,059, while also recording the highest average cost per work order at approximately $1,377.60.
A17: Recommended Actions
... A21: • Maintain focus on occupancy performance to support continued revenue growth.

Sheet Financial Performance
A1: Department | B1: Revenue | C1: Budgeted Cost | D1: Actual Cost | E1: Variance $ | F1: Variance %
A2: Food & Beverage | B2: =SUMIFS(tblFinancials[Revenue],tblFinancials[Department],A2) -> 9582413 | C2: =SUMIFS(tblFinancials[Budgeted Cost],tblFinancials[Department],'Financial Performance'!A2) -> 1909799 | D2: =SUMIFS(tblFinancials[Actual Cost],tblFinancials[Department],'Financial Performance'!A2) -> 1979412 | E2: =D2-C2 -> 69613 | F2: =E2/C2 -> 0.036450433
A3: Housekeeping | B3: =SUMIFS(tblFinancials[Revenue],tblFinancials[Department],A3) -> 9291840 | C3: =SUMIFS(tblFinancials[Budgeted Cost],tblFinancials[Department],'Financial Performance'!A3) -> 1770315 | D3: =SUMIFS(tblFinancials[Actual Cost],tblFinancials[Department],'Financial Performance'!A3) -> 1918443 | E3: =D3-C3 -> 148128 | F3: =E3/C3 -> 0.083673245
A4: Gaming Operations | B4: =SUMIFS(tblFinancials[Revenue],tblFinancials[Department],A4) -> 8410814 | C4: =SUMIFS(tblFinancials[Budgeted Cost],tblFinancials[Department],'Financial Performance'!A4) -> 2076662 | D4: =SUMIFS(tblFinancials[Actual Cost],tblFinancials[Department],'Financial Performance'!A4) -> 2179566 | E4: =D4-C4 -> 102904 | F4: =E4/C4 -> 0.049552599
A5: Entertainment & Events | B5: =SUMIFS(tblFinancials[Revenue],tblFinancials[Department],A5) -> 9740589 | C5: =SUMIFS(tblFinancials[Budgeted Cost],tblFinancials[Department],'Financial Performance'!A5) -> 1892016 | D5: =SUMIFS(tblFinancials[Actual Cost],tblFinancials[Department],'Financial Performance'!A5) -> 1922587 | E5: =D5-C5 -> 30571 | F5: =E5/C5 -> 0.016157897
A6: Facilities | B6: =SUMIFS(tblFinancials[Revenue],tblFinancials[Department],A6) -> 10303432 | C6: =SUMIFS(tblFinancials[Budgeted Cost],tblFinancials[Department],'Financial Performance'!A6) -> 1986002 | D6: =SUMIFS(tblFinancials[Actual Cost],tblFinancials[Department],'Financial Performance'!A6) -> 2007408 | E6: =D6-C6 -> 21406 | F6: =E6/C6 -> 0.010778438
A7: Total | B7: =SUM(B2:B6) -> 47329088 | C7: =SUM(C2:C6) -> 9634794 | D7: =SUM(D2:D6) -> 10007416 | E7: =D7-C7 -> 372622 | F7: =E7/C7 -> 0.03867462

Sheet Maintenance Review
A1: Department | B1: Work Orders | C1: Maintenance Cost | D1: Vendor Spend | E1: Avg Cost Per Work Order
A2: Gaming Operations | B2: =SUMIFS(tblMaintenance[Work Orders],tblMaintenance[Department],'Maintenance Review'!A2) -> 551 | C2: =SUMIFS(tblMaintenance[Maintenance Cost],tblMaintenance[Department],'Maintenance Review'!A2) -> 759059 | D2: =SUMIFS(tblMaintenance[Top Vendor Spend],tblMaintenance[Department],'Maintenance Review'!A2) -> 279960 | E2: =C2/B2 -> 1377.6025
A3: Housekeeping | B3: =SUMIFS(tblMaintenance[Work Orders],tblMaintenance[Department],'Maintenance Review'!A3) -> 530 | C3: =SUMIFS(tblMaintenance[Maintenance Cost],tblMaintenance[Department],'Maintenance Review'!A3) -> 622549 | D3: =SUMIFS(tblMaintenance[Top Vendor Spend],tblMaintenance[Department],'Maintenance Review'!A3) -> 290012 | E3: =C3/B3 -> 1174.6208
A4: Food & Beverage | B4: =SUMIFS(tblMaintenance[Work Orders],tblMaintenance[Department],'Maintenance Review'!A4) -> 547 | C4: =SUMIFS(tblMaintenance[Maintenance Cost],tblMaintenance[Department],'Maintenance Review'!A4) -> 597602 | D4: =SUMIFS(tblMaintenance[Top Vendor Spend],tblMaintenance[Department],'Maintenance Review'!A4) -> 241704 | E4: =C4/B4 -> 1092.5082
A5: Facilities | B5: =SUMIFS(tblMaintenance[Work Orders],tblMaintenance[Department],'Maintenance Review'!A5) -> 544 | C5: =SUMIFS(tblMaintenance[Maintenance Cost],tblMaintenance[Department],'Maintenance Review'!A5) -> 595892 | D5: =SUMIFS(tblMaintenance[Top Vendor Spend],tblMaintenance[Department],'Maintenance Review'!A5) -> 275987 | E5: =C5/B5 -> 1095.3897
A6: Entertainment & Events | B6: =SUMIFS(tblMaintenance[Work Orders],tblMaintenance[Department],'Maintenance Review'!A6) -> 540 | C6: =SUMIFS(tblMaintenance[Maintenance Cost],tblMaintenance[Department],'Maintenance Review'!A6) -> 591130 | D6: =SUMIFS(tblMaintenance[Top Vendor Spend],tblMaintenance[Department],'Maintenance Review'!A6) -> 234588 | E6: =C6/B6 -> 1094.6852
A7: Totals | B7: =SUM(B2:B6) -> 2712 | C7: =SUM(C2:C6) -> 3166232 | D7: =SUM(D2:D6) -> 1322251 | E7: =C7/B7 -> 1167.4897

Sheet Inventory & COGS Review
A1: Category | B1: Purchases | C1: COGS | D1: Shrinkage | E1: COGS % | F1: Shrinkage %
A2: Meat | B2: =SUMIFS(tblInventory[Purchases],tblInventory[Category],'Inventory & COGS Review'!A2) -> 738626 | C2: =SUMIFS(tblInventory[COGS],tblInventory[Category],'Inventory & COGS Review'!A2) -> 574753 | D2: =SUMIFS(tblInventory[Shrinkage],tblInventory[Category],'Inventory & COGS Review'!A2) -> 9126 | E2: =C2/B2 -> 0.77813806 | F2: =D2/B2 -> 0.012355373
A3: Seafood | B3: =SUMIFS(tblInventory[Purchases],tblInventory[Category],'Inventory & COGS Review'!A3) -> 619369 | C3: =SUMIFS(tblInventory[COGS],tblInventory[Category],'Inventory & COGS Review'!A3) -> 480526 | D3: =SUMIFS(tblInventory[Shrinkage],tblInventory[Category],'Inventory & COGS Review'!A3) -> 14481 | E3: =C3/B3 -> 0.77583153 | F3: =D3/B3 -> 0.023380247
A4: Beverage | B4: =SUMIFS(tblInventory[Purchases],tblInventory[Category],'Inventory & COGS Review'!A4) -> 682112 | C4: =SUMIFS(tblInventory[COGS],tblInventory[Category],'Inventory & COGS Review'!A4) -> 531754 | D4: =SUMIFS(tblInventory[Shrinkage],tblInventory[Category],'Inventory & COGS Review'!A4) -> 17856 | E4: =C4/B4 -> 0.77956992 | F4: =D4/B4 -> 0.026177519
A5: Produce | B5: =SUMIFS(tblInventory[Purchases],tblInventory[Category],'Inventory & COGS Review'!A5) -> 664336 | C5: =SUMIFS(tblInventory[COGS],tblInventory[Category],'Inventory & COGS Review'!A5) -> 518895 | D5: =SUMIFS(tblInventory[Shrinkage],tblInventory[Category],'Inventory & COGS Review'!A5) -> 15582 | E5: =C5/B5 -> 0.78107313 | F5: =D5/B5 -> 0.023454999
A6: Dairy | B6: =SUMIFS(tblInventory[Purchases],tblInventory[Category],'Inventory & COGS Review'!A6) -> 700641 | C6: =SUMIFS(tblInventory[COGS],tblInventory[Category],'Inventory & COGS Review'!A6) -> 582291 | D6: =SUMIFS(tblInventory[Shrinkage],tblInventory[Category],'Inventory & COGS Review'!A6) -> 15675 | E6: =C6/B6 -> 0.83108325 | F6: =D6/B6 -> 0.02237237
A7: Totals | B7: =SUM(B2:B6) -> 3405084 | C7: =SUM(C2:C6) -> 2688219 | D7: =SUM(D2:D6) -> 72720 | E7: =C7/B7 -> 0.78947215 | F7: =D7/B7 -> 0.021356301

Sheet KPI Trends
A1: Row Labels | B1: Sum of Revenue | C1: Sum of Budgeted Cost
A2: Jan | B2: 3834786 | C2: 730332
A3: Feb | B3: 3638227 | C3: 802374
A4: Mar | B4: 3074261 | C4: 763583
A5: Apr | B5: 4682017 | C5: 585838
A6: May | B6: 4842478 | C6: 978376
A7: Jun | B7: 4046154 | C7: 835659
A8: Jul | B8: 3737062 | C8: 929965
A9: Aug | B9: 3653011 | C9: 884550
A10: Sep | B10: 3680463 | C10: 670662
A11: Oct | B11: 4133812 | C11: 761140
A12: Nov | B12: 4079859 | C12: 796302
A13: Dec | B13: 3926958 | C13: 896013
A14: Grand Total | B14: 47329088 | C14: 9634794
A22: Month | B22: Revenue | C22: Occupancy % | D22: ADR | E22: RevPAR | F22: COGS | G22: Maintenance Cost
A23: Jan | B23: =SUMIFS(tblFinancials[Revenue],tblFinancials[Month],'KPI Trends'!A23) -> 3834786 | C23: 0.874 | D23: 271 | E23: 236.85 | F23: =SUMIFS(tblInventory[COGS],tblInventory[Month],'KPI Trends'!A23) -> 233315 | G23: =SUMIFS(tblMaintenance[Maintenance Cost],tblMaintenance[Month],'KPI Trends'!A23) -> 318006
A24: Feb | B24: =SUMIFS(tblFinancials[Revenue],tblFinancials[Month],'KPI Trends'!A24) -> 3638227 | C24: 0.945 | D24: 280 | E24: 264.6 | F24: =SUMIFS(tblInventory[COGS],tblInventory[Month],'KPI Trends'!A24) -> 221964 | G24: =SUMIFS(tblMaintenance[Maintenance Cost],tblMaintenance[Month],'KPI Trends'!A24) -> 202150
A25: Mar | B25: =SUMIFS(tblFinancials[Revenue],tblFinancials[Month],'KPI Trends'!A25) -> 3074261 | C25: 0.825 | D25: 142 | E25: 117.15 | F25: =SUMIFS(tblInventory[COGS],tblInventory[Month],'KPI Trends'!A25) -> 209944 | G25: =SUMIFS(tblMaintenance[Maintenance Cost],tblMaintenance[Month],'KPI Trends'!A25) -> 204180
A26: Apr | B26: =SUMIFS(tblFinancials[Revenue],tblFinancials[Month],'KPI Trends'!A26) -> 4682017 | C26: 0.868 | D26: 287 | E26: 249.12 | F26: =SUMIFS(tblInventory[COGS],tblInventory[Month],'KPI Trends'!A26) -> 185443 | G26: =SUMIFS(tblMaintenance[Maintenance Cost],tblMaintenance[Month],'KPI Trends'!A26) -> 304706
A27: May | B27: =SUMIFS(tblFinancials[Revenue],tblFinancials[Month],'KPI Trends'!A27) -> 4842478 | C27: 0.801 | D27: 198 | E27: 158.6 | F27: =SUMIFS(tblInventory[COGS],tblInventory[Month],'KPI Trends'!A27) -> 299466 | G27: =SUMIFS(tblMaintenance[Maintenance Cost],tblMaintenance[Month],'KPI Trends'!A27) -> 241405
A28: Jun | B28: =SUMIFS(tblFinancials[Revenue],tblFinancials[Month],'KPI Trends'!A28) -> 4046154 | C28: 0.882 | D28: 224 | E28: 197.57 | F28: =SUMIFS(tblInventory[COGS],tblInventory[Month],'KPI Trends'!A28) -> 172067 | G28: =SUMIFS(tblMaintenance[Maintenance Cost],tblMaintenance[Month],'KPI Trends'!A28) -> 305548
A29: Jul | B29: =SUMIFS(tblFinancials[Revenue],tblFinancials[Month],'KPI Trends'!A29) -> 3737062 | C29: 0.87 | D29: 229 | E29: 199.23 | F29: =SUMIFS(tblInventory[COGS],tblInventory[Month],'KPI Trends'!A29) -> 227766 | G29: =SUMIFS(tblMaintenance[Maintenance Cost],tblMaintenance[Month],'KPI Trends'!A29) -> 313061
A30: Aug | B30: =SUMIFS(tblFinancials[Revenue],tblFinancials[Month],'KPI Trends'!A30) -> 3653011 | C30: 0.917 | D30: 174 | E30: 159.56 | F30: =SUMIFS(tblInventory[COGS],tblInventory[Month],'KPI Trends'!A30) -> 189725 | G30: =SUMIFS(tblMaintenance[Maintenance Cost],tblMaintenance[Month],'KPI Trends'!A30) -> 271160
A31: Sep | B31: =SUMIFS(tblFinancials[Revenue],tblFinancials[Month],'KPI Trends'!A31) -> 3680463 | C31: 0.827 | D31: 243 | E31: 200.96 | F31: =SUMIFS(tblInventory[COGS],tblInventory[Month],'KPI Trends'!A31) -> 212393 | G31: =SUMIFS(tblMaintenance[Maintenance Cost],tblMaintenance[Month],'KPI Trends'!A31) -> 271424
A32: Oct | B32: =SUMIFS(tblFinancials[Revenue],tblFinancials[Month],'KPI Trends'!A32) -> 4133812 | C32: 0.956 | D32: 245 | E32: 234.22 | F32: =SUMIFS(tblInventory[COGS],tblInventory[Month],'KPI Trends'!A32) -> 220892 | G32: =SUMIFS(tblMaintenance[Maintenance Cost],tblMaintenance[Month],'KPI Trends'!A32) -> 309493
A33: Nov | B33: =SUMIFS(tblFinancials[Revenue],tblFinancials[Month],'KPI Trends'!A33) -> 4079859 | C33: 0.968 | D33: 241 | E33: 233.29 | F33: =SUMIFS(tblInventory[COGS],tblInventory[Month],'KPI Trends'!A33) -> 275141 | G33: =SUMIFS(tblMaintenance[Maintenance Cost],tblMaintenance[Month],'KPI Trends'!A33) -> 250451
A34: Dec | B34: =SUMIFS(tblFinancials[Revenue],tblFinancials[Month],'KPI Trends'!A34) -> 3926958 | C34: 0.851 | D34: 266 | E34: 226.37 | F34: =SUMIFS(tblInventory[COGS],tblInventory[Month],'KPI Trends'!A34) -> 240103 | G34: =SUMIFS(tblMaintenance[Maintenance Cost],tblMaintenance[Month],'KPI Trends'!A34) -> 174648

Sheet Financials
A1: Month | B1: Department | C1: Revenue | D1: Budgeted Cost | E1: Actual Cost
A2: Jan | B2: Food & Beverage | C2: 934845 | D2: 101679 | E2: 124005
A3: Jan | B3: Housekeeping | C3: 850806 | D3: 125425 | E3: 140112
A4: Jan | B4: Gaming Operations | C4: 350469 | D4: 177323 | E4: 181941
A5: Jan | B5: Entertainment & Events | C5: 947382 | D5: 140819 | E5: 125130
A6: Jan | B6: Facilities | C6: 751284 | D6: 185086 | E6: 171488
A7: Feb | B7: Food & Beverage | C7: 395457 | D7: 111113 | E7: 104977
A8: Feb | B8: Housekeeping | C8: 743774 | D8: 106043 | E8: 113004
A9: Feb | B9: Gaming Operations | C9: 401621 | D9: 240544 | E9: 222370
A10: Feb | B10: Entertainment & Events | C10: 930663 | D10: 213750 | E10: 198129
A11: Feb | B11: Facilities | C11: 1166712 | D11: 130924 | E11: 123332
A12: Mar | B12: Food & Beverage | C12: 377916 | D12: 139751 | E12: 161608
A13: Mar | B13: Housekeeping | C13: 766912 | D13: 200663 | E13: 203893
... A61: Dec | B61: Facilities | C61: 691792 | D61: 148122 | E61: 132490

Sheet Maintenance
A1: Month | B1: Department | C1: Work Orders | D1: Maintenance Cost | E1: Top Vendor Spend
A2: Jan | B2: Food & Beverage | C2: 74 | D2: 39573 | E2: 25156
A3: Jan | B3: Housekeeping | C3: 61 | D3: 86480 | E3: 34740
A4: Jan | B4: Gaming Operations | C4: 54 | D4: 75951 | E4: 32348
A5: Jan | B5: Entertainment & Events | C5: 36 | D5: 63384 | E5: 12717
A6: Jan | B6: Facilities | C6: 64 | D6: 52618 | E6: 15201
A7: Feb | B7: Food & Beverage | C7: 31 | D7: 34887 | E7: 26898
A8: Feb | B8: Housekeeping | C8: 29 | D8: 39351 | E8: 37466
A9: Feb | B9: Gaming Operations | C9: 56 | D9: 43963 | E9: 38680
A10: Feb | B10: Entertainment & Events | C10: 55 | D10: 29549 | E10: 11668
A11: Feb | B11: Facilities | C11: 26 | D11: 54400 | E11: 27973
A12: Mar | B12: Food & Beverage | C12: 68 | D12: 27860 | E12: 5473
A13: Mar | B13: Housekeeping | C13: 74 | D13: 35924 | E13: 27045
... A61: Dec | B61: Facilities | C61: 50 | D61: 26765 | E61: 18341

Sheet Inventory
A1: Month | B1: Category | C1: Purchases | D1: COGS | E1: Shrinkage
A2: Jan | B2: Meat | C2: 87807 | D2: 61134 | E2: 557
A3: Jan | B3: Seafood | C3: 23420 | D3: 20672 | E3: 935
A4: Jan | B4: Beverage | C4: 62873 | D4: 43231 | E4: 2464
A5: Jan | B5: Produce | C5: 69318 | D5: 55377 | E5: 784
A6: Jan | B6: Dairy | C6: 57995 | D6: 52901 | E6: 894
A7: Feb | B7: Meat | C7: 43732 | D7: 32422 | E7: 980
A8: Feb | B8: Seafood | C8: 55140 | D8: 41031 | E8: 741
A9: Feb | B9: Beverage | C9: 89265 | D9: 70562 | E9: 1606
A10: Feb | B10: Produce | C10: 72068 | D10: 47565 | E10: 823
A11: Feb | B11: Dairy | C11: 32640 | D11: 30384 | E11: 887
A12: Mar | B12: Meat | C12: 21261 | D12: 19053 | E12: 1338
A13: Mar | B13: Seafood | C13: 33096 | D13: 27118 | E13: 2303
... A61: Dec | B61: Dairy | C61: 72127 | D61: 60004 | E61: 1902

Sheet Resort KPIs
A1: Month | B1: Occupancy % | C1: ADR | D1: RevPAR | E1: Guest Count
A2: Jan | B2: 87.4 | C2: 271 | D2: 236.85 | E2: 31732
A3: Feb | B3: 94.5 | C3: 280 | D3: 264.6 | E3: 34392
A4: Mar | B4: 82.5 | C4: 142 | D4: 117.15 | E4: 21371
A5: Apr | B5: 86.8 | C5: 287 | D5: 249.12 | E5: 20565
A6: May | B6: 80.1 | C6: 198 | D6: 158.6 | E6: 22505
A7: Jun | B7: 88.2 | C7: 224 | D7: 197.57 | E7: 48776
A8: Jul | B8: 87 | C8: 229 | D8: 199.23 | E8: 48666
A9: Aug | B9: 91.7 | C9: 174 | D9: 159.56 | E9: 44438
A10: Sep | B10: 82.7 | C10: 243 | D10: 200.96 | E10: 34905
A11: Oct | B11: 95.6 | C11: 245 | D11: 234.22 | E11: 47767
A12: Nov | B12: 96.8 | C12: 241 | D12: 233.29 | E12: 30592
A13: Dec | B13: 85.1 | C13: 266 | D13: 226.37 | E13: 45510
